ytsphinx-1.2.dev20200430-py3.7-nspkg.pth
ytsphinx/youtube.py
ytsphinx-1.2.dev20200430.dist-info/METADATA
ytsphinx-1.2.dev20200430.dist-info/WHEEL
ytsphinx-1.2.dev20200430.dist-info/namespace_packages.txt
ytsphinx-1.2.dev20200430.dist-info/top_level.txt
ytsphinx-1.2.dev20200430.dist-info/RECORD
